Metadata-Version: 2.1
Name: simkit
Version: 0.0.0
Summary: SimKit: A Simulation Toolkit For Computer Animation
Home-page: https://github.com/otmanon/pal
Author: Otman Benchekroun
Author-email: otman.benchekroun@mail.utoronto.ca
License: MIT
Requires-Dist: scipy
Requires-Dist: numpy
Requires-Dist: polyscope
Requires-Dist: libigl
